cherrypick/__init__.py
cherrypick/cherrypick.py
cherrypick-0.2.2.dist-info/AUTHORS.rst
cherrypick-0.2.2.dist-info/LICENSE
cherrypick-0.2.2.dist-info/METADATA
cherrypick-0.2.2.dist-info/WHEEL
cherrypick-0.2.2.dist-info/top_level.txt
cherrypick-0.2.2.dist-info/RECORD
