Metadata-Version: 2.1
Name: cherrypick
Version: 0.2.2
Summary: Some tools to help the process of feature selection
Home-page: https://github.com/lgpcarames/cherrypick
Author: Lucas Carames
Author-email: lgpcarames@gmail.com
License: MIT license
Keywords: cherrypick
Classifier: Development Status :: 2 - Pre-Alpha
Classifier: License :: OSI Approved :: MIT License
Classifier: Natural Language :: English
Classifier: Programming Language :: Python :: 3
Classifier: Programming Language :: Python :: 3.6
Classifier: Programming Language :: Python :: 3.7
Classifier: Programming Language :: Python :: 3.8
Classifier: Programming Language :: Python :: 3.9
Requires-Python: >=3.6
License-File: LICENSE
License-File: AUTHORS.rst
Requires-Dist: pip >=21.1
Requires-Dist: bump2version >=0.5.11
Requires-Dist: wheel >=0.38.1
Requires-Dist: watchdog >=0.9.0
Requires-Dist: flake8 >=3.7.8
Requires-Dist: tox >=3.14.0
Requires-Dist: coverage >=4.5.4
Requires-Dist: Sphinx >=1.8.5
Requires-Dist: twine >=1.14.0
Requires-Dist: pandas >=1.5.3
Requires-Dist: scikit-learn >=1.2.1
Requires-Dist: numpy >=1.23.5
Requires-Dist: matplotlib >=3.7.0
Requires-Dist: optuna >=3.1.1
Requires-Dist: lightgbm >=3.3.5
Requires-Dist: tqdm >=4.64.1
Requires-Dist: shap >=0.41.0
